datls/__init__.py
datls/cli.py
datls-0.3.0.data/scripts/datls
datls-0.3.0.dist-info/DESCRIPTION.rst
datls-0.3.0.dist-info/METADATA
datls-0.3.0.dist-info/RECORD
datls-0.3.0.dist-info/WHEEL
datls-0.3.0.dist-info/metadata.json
datls-0.3.0.dist-info/namespace_packages.txt
datls-0.3.0.dist-info/top_level.txt
datls-0.3.0.dist-info/zip-safe
